README
setup.py
django_vendors.egg-info/PKG-INFO
django_vendors.egg-info/SOURCES.txt
django_vendors.egg-info/dependency_links.txt
django_vendors.egg-info/not-zip-safe
django_vendors.egg-info/top_level.txt
vendors/__init__.py
vendors/admin.py
vendors/context_processors.py
vendors/forms.py
vendors/managers.py
vendors/models.py
vendors/urls.py
vendors/views.py
vendors/templatetags/__init__.py
vendors/templatetags/vendor_tags.py