Metadata-Version: 1.0
Name: django-vendors
Version: 0.2-0
Summary: Vendor management for the Django framework.
Home-page: http://github.com/powellc/django-vendors/
Author: Colin Powell
Author-email: colin.powel@me.com
License: UNKNOWN
Platform: UNKNOWN
Classifier: Development Status :: 5 - Production/Stable
Classifier: Environment :: Web Environment
Classifier: Framework :: Django
Classifier: Intended Audience :: Developers
Classifier: License :: OSI Approved :: BSD License
Classifier: Operating System :: OS Independent
Classifier: Programming Language :: Python
Classifier: Topic :: Utilities
